Poker65/__init__.py
Poker65/card.py
Poker65/hands.py
poker65-0.0.3.dist-info/licenses/LICENSE
poker65-0.0.3.dist-info/METADATA
poker65-0.0.3.dist-info/WHEEL
poker65-0.0.3.dist-info/top_level.txt
poker65-0.0.3.dist-info/RECORD
