Metadata-Version: 2.4
Name: Poker65
Version: 0.0.3
Summary: A package for finding the best poker hand from 7 cards.
Author-email: Daniel Li <danielgongli.65@gmail.com>
License-Expression: GPL-3.0-or-later
Project-URL: Homepage, https://github.com/FallingSky65/Poker65
Classifier: Programming Language :: Python :: 3
Classifier: Operating System :: OS Independent
Requires-Python: >=3.10
License-File: LICENSE
Dynamic: license-file
